Metadata-Version: 2.1
Name: odoo13-addon-github-connector-odoo
Version: 13.0.2.0.0
Summary: Analyze Odoo modules information from Github repositories
Home-page: UNKNOWN
Author: Odoo Community Association (OCA), Sylvain LE GAL, GRAP
Author-email: support@odoo-community.org
License: AGPL-3
Platform: UNKNOWN
Classifier: Programming Language :: Python
Classifier: Framework :: Odoo
Classifier: Framework :: Odoo :: 13.0
Classifier: License :: OSI Approved :: GNU Affero General Public License v3
Requires-Python: >=3.5
Requires-Dist: odoo13-addon-github-connector
Requires-Dist: odoo (<13.1dev,>=13.0a)
Requires-Dist: pathspec
